{
    "Ar36": {
        "error": 0.004151983162588069,
        "error_type": "SEM",
        "filter_outliers_dict": {
            "filter_outliers": true,
            "iterations": 1,
            "std_devs": 2
        },
        "fit": "Linear",
        "value": 0.06454073177337366
    },
    "Ar37": {
        "error": 0.009160267194545211,
        "error_type": "SEM",
        "filter_outliers_dict": {
            "filter_outliers": true,
            "iterations": 1,
            "std_devs": 2
        },
        "fit": "Linear",
        "value": -0.0004596530511313474
    },
    "Ar38": {
        "error": 0.004569370320294344,
        "error_type": "SEM",
        "filter_outliers_dict": {
            "filter_outliers": true,
            "iterations": 1,
            "std_devs": 2
        },
        "fit": "Linear",
        "value": 0.01056608061628658
    },
    "Ar39": {
        "error": 0.014966541247536793,
        "error_type": "SEM",
        "filter_outliers_dict": {
            "filter_outliers": true,
            "iterations": 1,
            "std_devs": 2
        },
        "fit": "Parabolic",
        "value": -0.09720605464951239
    },
    "Ar40": {
        "error": 0.017873285674129356,
        "error_type": "SEM",
        "filter_outliers_dict": {
            "filter_outliers": true,
            "iterations": 1,
            "std_devs": 2
        },
        "fit": "Parabolic",
        "value": 16.66333633383388
    }
}